omni_authify/__init__.py
omni_authify/settings.py
omni_authify/core/__init__.py
omni_authify/core/exceptions.py
omni_authify/core/oauth.py
omni_authify/core/utils.py
omni_authify/frameworks/__init__.py
omni_authify/frameworks/django.py
omni_authify/frameworks/drf.py
omni_authify/frameworks/fastapi.py
omni_authify/frameworks/flask.py
omni_authify/providers/__init__.py
omni_authify/providers/apple.py
omni_authify/providers/base.py
omni_authify/providers/facebook.py
omni_authify/providers/github.py
omni_authify/providers/google.py
omni_authify/providers/instagram.py
omni_authify/providers/linkedin.py
omni_authify/providers/telegram.py
omni_authify/providers/twitter.py
omni_authify-1.1.8.dist-info/LICENSE
omni_authify-1.1.8.dist-info/METADATA
omni_authify-1.1.8.dist-info/WHEEL
omni_authify-1.1.8.dist-info/top_level.txt
omni_authify-1.1.8.dist-info/RECORD
