Metadata-Version: 2.1
Name: omni-authify
Version: 1.1.8
Summary: A Python library for OAuth2 authentication across frameworks and providers
Home-page: https://github.com/Omni-Libraries/omni-authify.git
Author: Mukhsin Mukhtorov
Author-email: mukhsinmukhtorov@arizona.edu
Maintainer: Mukhsin Mukhtorov
Maintainer-email: mukhsinmukhtorov@arizona.edu
License: MIT
Download-URL: https://github.com/Omni-Libraries/omni-authify.git
Keywords: Oauth2,facebook-login,instagram-login,twitter-login,x-login,github-login,google-login,linkedin-login,telegram-login,oauth2-django,oauth2-djangorestframework,oauth2-fastapi,oauth2-flask
Platform: UNKNOWN
Classifier: Development Status :: 4 - Beta
Classifier: Programming Language :: Python :: 3.12
Classifier: License :: OSI Approved :: MIT License
Classifier: Operating System :: OS Independent
Classifier: Intended Audience :: Developers
Classifier: Topic :: Software Development :: Build Tools
Requires-Python: >=3.8
Requires-Dist: requests
Requires-Dist: python-dotenv>=1.0.1
Provides-Extra: django
Requires-Dist: Django>=4.2; extra == "django"
Provides-Extra: drf
Requires-Dist: djangorestframework>=3.12.3; extra == "drf"
Provides-Extra: fastapi
Requires-Dist: fastapi>=0.115.0; extra == "fastapi"
Provides-Extra: flask
Requires-Dist: Flask>=3.0.0; extra == "flask"
